{
"meta":{"test_sets":[],"test_metrics":[],"learn_metrics":[{"best_value":"Min","name":"MultiClass"}],"launch_mode":"Train","parameters":"","iteration_count":100,"learn_sets":["learn"],"name":"experiment"},
"iterations":[
{"learn":[0.612090461],"iteration":0,"passed_time":0.1628999955,"remaining_time":16.12709956},
{"learn":[0.5461346532],"iteration":1,"passed_time":0.1643710713,"remaining_time":8.054182493},
{"learn":[0.4933534411],"iteration":2,"passed_time":0.1654662762,"remaining_time":5.350076262},
{"learn":[0.4481694676],"iteration":3,"passed_time":0.1665515903,"remaining_time":3.997238166},
{"learn":[0.4077303345],"iteration":4,"passed_time":0.1676915711,"remaining_time":3.186139851},
{"learn":[0.3752323523],"iteration":5,"passed_time":0.1690338306,"remaining_time":2.64819668},
{"learn":[0.3453422785],"iteration":6,"passed_time":0.1706487503,"remaining_time":2.267190539},
{"learn":[0.3192653538],"iteration":7,"passed_time":0.1718295067,"remaining_time":1.976039327},
{"learn":[0.296975923],"iteration":8,"passed_time":0.1733776537,"remaining_time":1.753040721},
{"learn":[0.2767512836],"iteration":9,"passed_time":0.1747787507,"remaining_time":1.573008756},
{"learn":[0.2584111161],"iteration":10,"passed_time":0.1760571634,"remaining_time":1.424462504},
{"learn":[0.244023474],"iteration":11,"passed_time":0.1773854126,"remaining_time":1.300826359},
{"learn":[0.229451912],"iteration":12,"passed_time":0.1795942217,"remaining_time":1.201899792},
{"learn":[0.2171710828],"iteration":13,"passed_time":0.1805860611,"remaining_time":1.109314376},
{"learn":[0.2062248403],"iteration":14,"passed_time":0.1817458463,"remaining_time":1.029893129},
{"learn":[0.1964899673],"iteration":15,"passed_time":0.1828615849,"remaining_time":0.9600233209},
{"learn":[0.1874793381],"iteration":16,"passed_time":0.1839771148,"remaining_time":0.8982412076},
{"learn":[0.1796331509],"iteration":17,"passed_time":0.1853123066,"remaining_time":0.8442005078},
{"learn":[0.1721961963],"iteration":18,"passed_time":0.1865155076,"remaining_time":0.7951450586},
{"learn":[0.1657866567],"iteration":19,"passed_time":0.1884600057,"remaining_time":0.7538400226},
{"learn":[0.1601862267],"iteration":20,"passed_time":0.1901203943,"remaining_time":0.7152148168},
{"learn":[0.1550743375],"iteration":21,"passed_time":0.191512414,"remaining_time":0.6789985587},
{"learn":[0.1505438503],"iteration":22,"passed_time":0.1930979345,"remaining_time":0.6464583025},
{"learn":[0.1474364099],"iteration":23,"passed_time":0.1945197324,"remaining_time":0.6159791527},
{"learn":[0.1434805669],"iteration":24,"passed_time":0.1959928669,"remaining_time":0.5879786008},
{"learn":[0.1399863047],"iteration":25,"passed_time":0.1973363178,"remaining_time":0.5616495199},
{"learn":[0.1366064004],"iteration":26,"passed_time":0.1987548948,"remaining_time":0.5373743451},
{"learn":[0.1335975109],"iteration":27,"passed_time":0.199742727,"remaining_time":0.5136241551},
{"learn":[0.1311112968],"iteration":28,"passed_time":0.2013003633,"remaining_time":0.4928388204},
{"learn":[0.1289446522],"iteration":29,"passed_time":0.2030777446,"remaining_time":0.4738480708},
{"learn":[0.1284027025],"iteration":30,"passed_time":0.2045880994,"remaining_time":0.4553735117},
{"learn":[0.1261936269],"iteration":31,"passed_time":0.2062129595,"remaining_time":0.4382025389},
{"learn":[0.1244102506],"iteration":32,"passed_time":0.2077776039,"remaining_time":0.4218514988},
{"learn":[0.123199112],"iteration":33,"passed_time":0.2088001582,"remaining_time":0.4053179541},
{"learn":[0.1221404663],"iteration":34,"passed_time":0.2102527901,"remaining_time":0.3904694673},
{"learn":[0.1208856671],"iteration":35,"passed_time":0.2117422728,"remaining_time":0.3764307073},
{"learn":[0.1197409549],"iteration":36,"passed_time":0.2131531874,"remaining_time":0.3629365083},
{"learn":[0.1190442326],"iteration":37,"passed_time":0.2144121545,"remaining_time":0.3498303573},
{"learn":[0.1186424279],"iteration":38,"passed_time":0.2157887281,"remaining_time":0.3375157029},
{"learn":[0.1171162255],"iteration":39,"passed_time":0.217736156,"remaining_time":0.326604234},
{"learn":[0.1159160998],"iteration":40,"passed_time":0.2193903439,"remaining_time":0.3157080559},
{"learn":[0.1156569859],"iteration":41,"passed_time":0.2207462234,"remaining_time":0.3048400229},
{"learn":[0.1144108744],"iteration":42,"passed_time":0.222181245,"remaining_time":0.2945193248},
{"learn":[0.1136206973],"iteration":43,"passed_time":0.2236032993,"remaining_time":0.2845860173},
{"learn":[0.11290817],"iteration":44,"passed_time":0.2250536817,"remaining_time":0.2750656109},
{"learn":[0.1122682657],"iteration":45,"passed_time":0.226602225,"remaining_time":0.2660113076},
{"learn":[0.1118589582],"iteration":46,"passed_time":0.2280016851,"remaining_time":0.2571082832},
{"learn":[0.1113255815],"iteration":47,"passed_time":0.229563223,"remaining_time":0.2486934916},
{"learn":[0.1108291729],"iteration":48,"passed_time":0.2311413623,"remaining_time":0.2405757036},
{"learn":[0.11018743],"iteration":49,"passed_time":0.2331899645,"remaining_time":0.2331899645},
{"learn":[0.1094383854],"iteration":50,"passed_time":0.2346501493,"remaining_time":0.2254481826},
{"learn":[0.1089778009],"iteration":51,"passed_time":0.2358865814,"remaining_time":0.2177414598},
{"learn":[0.1085156538],"iteration":52,"passed_time":0.2370333,"remaining_time":0.2101993415},
{"learn":[0.1080309313],"iteration":53,"passed_time":0.2381161879,"remaining_time":0.2028397156},
{"learn":[0.1077445206],"iteration":54,"passed_time":0.2392536176,"remaining_time":0.1957529599},
{"learn":[0.1072005383],"iteration":55,"passed_time":0.2405402342,"remaining_time":0.1889958983},
{"learn":[0.1060505539],"iteration":56,"passed_time":0.2415824856,"remaining_time":0.1822464365},
{"learn":[0.1058210101],"iteration":57,"passed_time":0.2425222382,"remaining_time":0.1756195518},
{"learn":[0.105484619],"iteration":58,"passed_time":0.2436003585,"remaining_time":0.1692816051},
{"learn":[0.1050804219],"iteration":59,"passed_time":0.2446591937,"remaining_time":0.1631061292},
{"learn":[0.1047523246],"iteration":60,"passed_time":0.2457968578,"remaining_time":0.1571488108},
{"learn":[0.1043718183],"iteration":61,"passed_time":0.2476963572,"remaining_time":0.1518138963},
{"learn":[0.1039353593],"iteration":62,"passed_time":0.2490254258,"remaining_time":0.1462530279},
{"learn":[0.1036304411],"iteration":63,"passed_time":0.2504596036,"remaining_time":0.140883527},
{"learn":[0.1030143365],"iteration":64,"passed_time":0.2521696696,"remaining_time":0.1357836683},
{"learn":[0.1027115358],"iteration":65,"passed_time":0.2536481374,"remaining_time":0.1306672223},
{"learn":[0.1021698572],"iteration":66,"passed_time":0.2551660095,"remaining_time":0.1256787808},
{"learn":[0.10163695],"iteration":67,"passed_time":0.2567100746,"remaining_time":0.120804741},
{"learn":[0.1010065463],"iteration":68,"passed_time":0.2582992392,"remaining_time":0.1160474843},
{"learn":[0.1006668477],"iteration":69,"passed_time":0.2598295663,"remaining_time":0.1113555284},
{"learn":[0.1000693953],"iteration":70,"passed_time":0.2612953659,"remaining_time":0.1067262762},
{"learn":[0.09956701768],"iteration":71,"passed_time":0.2630792875,"remaining_time":0.1023086118},
{"learn":[0.09905818974],"iteration":72,"passed_time":0.2646303831,"remaining_time":0.09787699102},
{"learn":[0.09886531798],"iteration":73,"passed_time":0.265961487,"remaining_time":0.09344592785},
{"learn":[0.09854649509],"iteration":74,"passed_time":0.2672342792,"remaining_time":0.08907809306},
{"learn":[0.09821275323],"iteration":75,"passed_time":0.2685024552,"remaining_time":0.08479024901},
{"learn":[0.09796734702],"iteration":76,"passed_time":0.2702815322,"remaining_time":0.08073344468},
{"learn":[0.09767129344],"iteration":77,"passed_time":0.271993655,"remaining_time":0.0767161591},
{"learn":[0.09752963207],"iteration":78,"passed_time":0.2736194144,"remaining_time":0.07273427472},
{"learn":[0.09717311808],"iteration":79,"passed_time":0.2748720596,"remaining_time":0.06871801491},
{"learn":[0.09665970008],"iteration":80,"passed_time":0.276191667,"remaining_time":0.06478569967},
{"learn":[0.09631416669],"iteration":81,"passed_time":0.2778487608,"remaining_time":0.06099119139},
{"learn":[0.09592888972],"iteration":82,"passed_time":0.2794497409,"remaining_time":0.05723669392},
{"learn":[0.09544344412],"iteration":83,"passed_time":0.2812312718,"remaining_time":0.0535678613},
{"learn":[0.09519721568],"iteration":84,"passed_time":0.2827093857,"remaining_time":0.04988989159},
{"learn":[0.09475225705],"iteration":85,"passed_time":0.2842369814,"remaining_time":0.0462711365},
{"learn":[0.0945598432],"iteration":86,"passed_time":0.2859707421,"remaining_time":0.04273126032},
{"learn":[0.09436525236],"iteration":87,"passed_time":0.2872775005,"remaining_time":0.03917420462},
{"learn":[0.0941202069],"iteration":88,"passed_time":0.2891309766,"remaining_time":0.03573528924},
{"learn":[0.09373563417],"iteration":89,"passed_time":0.2905170163,"remaining_time":0.03227966848},
{"learn":[0.09323042124],"iteration":90,"passed_time":0.2917739946,"remaining_time":0.02885676869},
{"learn":[0.09266441707],"iteration":91,"passed_time":0.2936951735,"remaining_time":0.02553871074},
{"learn":[0.09220157743],"iteration":92,"passed_time":0.2956420543,"remaining_time":0.02225262774},
{"learn":[0.0919472611],"iteration":93,"passed_time":0.2973895806,"remaining_time":0.01898231365},
{"learn":[0.09166656426],"iteration":94,"passed_time":0.2989478375,"remaining_time":0.01573409671},
{"learn":[0.09105607247],"iteration":95,"passed_time":0.3005282131,"remaining_time":0.01252200888},
{"learn":[0.09074010014],"iteration":96,"passed_time":0.302081707,"remaining_time":0.009342733207},
{"learn":[0.09050236772],"iteration":97,"passed_time":0.3034414945,"remaining_time":0.006192683562},
{"learn":[0.09024923108],"iteration":98,"passed_time":0.3047943847,"remaining_time":0.003078731158},
{"learn":[0.0899640254],"iteration":99,"passed_time":0.3062508918,"remaining_time":0}
]}